{"version":1,"resource":"vscode-remote://uwidcit-info2602a2-54yxl57ljoz.ws-us110.gitpod.io/workspace/info2602a2/App/app.py","entries":[{"id":"jlB7.py","timestamp":1710984564099},{"id":"0YLZ.py","timestamp":1710984619195},{"id":"4LfX.py","timestamp":1710984693579},{"id":"XD4H.py","source":"undoRedo.source","timestamp":1710984708739},{"id":"bdpf.py","timestamp":1710984728655},{"id":"bqld.py","timestamp":1710984768823},{"id":"kCyN.py","timestamp":1710984782755},{"id":"Bhtq.py","timestamp":1710984935303},{"id":"xKZh.py","timestamp":1710984974759},{"id":"1VWM.py","timestamp":1710985095847},{"id":"4I1I.py","timestamp":1710985123663},{"id":"W411.py","timestamp":1710986265166},{"id":"Vc3n.py","timestamp":1710986307194},{"id":"Xnrg.py","source":"undoRedo.source","timestamp":1710986318014},{"id":"g7oD.py","timestamp":1710987489032},{"id":"Habf.py","source":"undoRedo.source","timestamp":1710987495788},{"id":"sdBV.py","timestamp":1710988585771},{"id":"i1L3.py","timestamp":1710988656567},{"id":"7Cae.py","timestamp":1710988696491},{"id":"Vm5k.py","timestamp":1710988730739},{"id":"2Uba.py","timestamp":1710989021943},{"id":"INJx.py","timestamp":1710990290398},{"id":"elEH.py","source":"undoRedo.source","timestamp":1710990295914},{"id":"wPux.py","timestamp":1710990311970},{"id":"ux0t.py","timestamp":1710990377954},{"id":"QPPA.py","timestamp":1710990432574},{"id":"ed0s.py","timestamp":1710990458806},{"id":"vP9k.py","timestamp":1710990502150},{"id":"vNCY.py","timestamp":1710990524270},{"id":"3neE.py","timestamp":1710990563438},{"id":"KEes.py","timestamp":1710990850737},{"id":"m0km.py","timestamp":1710990967373},{"id":"jDZ9.py","timestamp":1710990990757},{"id":"X4Vv.py","timestamp":1710991004421},{"id":"uiTw.py","timestamp":1710993157007},{"id":"FEvt.py","timestamp":1710993191639},{"id":"1rBu.py","timestamp":1710993231475},{"id":"1cov.py","timestamp":1710993326795},{"id":"hi6y.py","timestamp":1710993348587},{"id":"Swgm.py","timestamp":1710993372535},{"id":"JN0v.py","timestamp":1710993395167},{"id":"VLyU.py","timestamp":1710993412439},{"id":"sbQz.py","timestamp":1710993442767},{"id":"ejEy.py","timestamp":1710993503211},{"id":"qrwn.py","timestamp":1710993689799},{"id":"9gQI.py","timestamp":1710993738107},{"id":"TGuy.py","timestamp":1710993761343},{"id":"uJAi.py","timestamp":1710993808123},{"id":"1Ph7.py","timestamp":1711033629433},{"id":"6Zyq.py","timestamp":1711033708357}]}